ament_cmake_pep257/_dummy.cpython-311-x86_64-linux-gnu.so
ros_ament_cmake_pep257-0.17.3.data/data/share/ament_cmake_pep257/local_setup.bash
ros_ament_cmake_pep257-0.17.3.data/data/share/ament_cmake_pep257/local_setup.dsv
ros_ament_cmake_pep257-0.17.3.data/data/share/ament_cmake_pep257/local_setup.sh
ros_ament_cmake_pep257-0.17.3.data/data/share/ament_cmake_pep257/local_setup.zsh
ros_ament_cmake_pep257-0.17.3.data/data/share/ament_cmake_pep257/package.dsv
ros_ament_cmake_pep257-0.17.3.data/data/share/ament_cmake_pep257/package.xml
ros_ament_cmake_pep257-0.17.3.data/data/share/ament_cmake_pep257/cmake/ament_cmake_pep257-extras.cmake
ros_ament_cmake_pep257-0.17.3.data/data/share/ament_cmake_pep257/cmake/ament_cmake_pep257Config-version.cmake
ros_ament_cmake_pep257-0.17.3.data/data/share/ament_cmake_pep257/cmake/ament_cmake_pep257Config.cmake
ros_ament_cmake_pep257-0.17.3.data/data/share/ament_cmake_pep257/cmake/ament_cmake_pep257_lint_hook.cmake
ros_ament_cmake_pep257-0.17.3.data/data/share/ament_cmake_pep257/cmake/ament_pep257.cmake
ros_ament_cmake_pep257-0.17.3.data/data/share/ament_cmake_pep257/environment/ament_prefix_path.dsv
ros_ament_cmake_pep257-0.17.3.data/data/share/ament_cmake_pep257/environment/ament_prefix_path.sh
ros_ament_cmake_pep257-0.17.3.data/data/share/ament_cmake_pep257/environment/path.dsv
ros_ament_cmake_pep257-0.17.3.data/data/share/ament_cmake_pep257/environment/path.sh
ros_ament_cmake_pep257-0.17.3.data/data/share/ament_index/resource_index/package_run_dependencies/ament_cmake_pep257
ros_ament_cmake_pep257-0.17.3.data/data/share/ament_index/resource_index/packages/ament_cmake_pep257
ros_ament_cmake_pep257-0.17.3.data/data/share/ament_index/resource_index/parent_prefix_path/ament_cmake_pep257
ros_ament_cmake_pep257-0.17.3.dist-info/METADATA
ros_ament_cmake_pep257-0.17.3.dist-info/WHEEL
ros_ament_cmake_pep257-0.17.3.dist-info/top_level.txt
ros_ament_cmake_pep257-0.17.3.dist-info/RECORD
