Metadata-Version: 2.4
Name: ros-ament-cmake-pep257
Version: 0.17.3
Summary: Wheel for the ament_cmake_pep257 (ros-ament-cmake-pep257) ROS 2 package.
Dynamic: description
Dynamic: description-content-type
Dynamic: summary
